odoo/addons/account_invoice_report_grouped_by_picking_sale_mrp/README.rst
odoo/addons/account_invoice_report_grouped_by_picking_sale_mrp/__init__.py
odoo/addons/account_invoice_report_grouped_by_picking_sale_mrp/__manifest__.py
odoo/addons/account_invoice_report_grouped_by_picking_sale_mrp/i18n/account_invoice_report_grouped_by_picking_sale_mrp.pot
odoo/addons/account_invoice_report_grouped_by_picking_sale_mrp/i18n/es.po
odoo/addons/account_invoice_report_grouped_by_picking_sale_mrp/models/__init__.py
odoo/addons/account_invoice_report_grouped_by_picking_sale_mrp/models/account_move.py
odoo/addons/account_invoice_report_grouped_by_picking_sale_mrp/readme/CONTRIBUTORS.rst
odoo/addons/account_invoice_report_grouped_by_picking_sale_mrp/readme/DESCRIPTION.rst
odoo/addons/account_invoice_report_grouped_by_picking_sale_mrp/readme/USAGE.rst
odoo/addons/account_invoice_report_grouped_by_picking_sale_mrp/static/description/icon.png
odoo/addons/account_invoice_report_grouped_by_picking_sale_mrp/static/description/index.html
odoo/addons/account_invoice_report_grouped_by_picking_sale_mrp/tests/__init__.py
odoo/addons/account_invoice_report_grouped_by_picking_sale_mrp/tests/test_report_grouped_sale_mrp.py
odoo_addon_account_invoice_report_grouped_by_picking_sale_mrp-15.0.1.0.1.dist-info/METADATA
odoo_addon_account_invoice_report_grouped_by_picking_sale_mrp-15.0.1.0.1.dist-info/WHEEL
odoo_addon_account_invoice_report_grouped_by_picking_sale_mrp-15.0.1.0.1.dist-info/top_level.txt
odoo_addon_account_invoice_report_grouped_by_picking_sale_mrp-15.0.1.0.1.dist-info/RECORD
